Metadata-Version: 2.1
Name: csvlogging-pkg-shri1900
Version: 0.0.2
Summary: A csv logging package
Home-page: https://github.com/shri1900/cpplibrary.git
Author: Shrikant Thombre
Author-email: shri1900@gmail.com
License: UNKNOWN
Platform: UNKNOWN
Classifier: Programming Language :: Python :: 3
Classifier: License :: OSI Approved :: MIT License
Classifier: Operating System :: OS Independent
Requires-Python: >=3.6
License-File: LICENSE
